graphene_directives/__init__.py
graphene_directives/constants.py
graphene_directives/data_models/__init__.py
graphene_directives/data_models/custom_directive_meta.py
graphene_directives/data_models/schema_directive.py
graphene_directives/directive.py
graphene_directives/exceptions.py
graphene_directives/main.py
graphene_directives/parsers.py
graphene_directives/schema.py
graphene_directives/utils.py
graphene_directives-0.5.0.dist-info/METADATA
graphene_directives-0.5.0.dist-info/WHEEL
graphene_directives-0.5.0.dist-info/licenses/LICENSE.md
graphene_directives-0.5.0.dist-info/RECORD
