Metadata-Version: 2.4
Name: graphene-directives
Version: 0.5.0
Summary: Schema Directives implementation for graphene
License: MIT
License-File: LICENSE.md
Keywords: graphene-directives,graphene,graphql,graphql-directives,graphql-custom-directives
Author: Strollby
Author-email: developers@strollby.com
Requires-Python: >=3.9,<4
Classifier: License :: OSI Approved :: MIT License
Classifier: Programming Language :: Python :: 3
Classifier: Programming Language :: Python :: 3.9
Classifier: Programming Language :: Python :: 3.10
Classifier: Programming Language :: Python :: 3.11
Classifier: Programming Language :: Python :: 3.12
Classifier: Programming Language :: Python :: 3.13
Classifier: Programming Language :: Python :: 3.14
Requires-Dist: graphene (>=3)
Project-URL: Documentation, https://github.com/strollby/graphene-directives
Project-URL: Homepage, https://github.com/strollby/graphene-directives
Project-URL: Repository, https://github.com/strollby/graphene-directives
